LICENSE
MANIFEST.in
README.rst
pyproject.toml
setup.cfg
setup.py
bcmr/__init__.py
bcmr/admin.py
bcmr/apps.py
bcmr/auth.py
bcmr/filters.py
bcmr/forms.py
bcmr/models.py
bcmr/serializers.py
bcmr/signals.py
bcmr/tests.py
bcmr/urls.py
bcmr/utils.py
bcmr/views.py
bcmr/migrations/0001_initial.py
bcmr/migrations/0002_authtoken.py
bcmr/migrations/0003_auto_20230213_0237.py
bcmr/migrations/0004_auto_20230214_0401.py
bcmr/migrations/0005_auto_20230227_0612.py
bcmr/migrations/0006_auto_20230330_0203.py
bcmr/migrations/0007_auto_20230330_0225.py
bcmr/migrations/0008_auto_20230331_0131.py
bcmr/migrations/0009_auto_20230331_0133.py
bcmr/migrations/0010_tokenhistory.py
bcmr/migrations/0011_auto_20230502_0839.py
bcmr/migrations/0012_remove_tokenhistory_category.py
bcmr/migrations/__init__.py
bcmr/templates/bcmr/create_token.html
bcmr/templates/docs/swagger-ui.html
django-bcmr/__init__.py
django-bcmr/asgi.py
django-bcmr/settings.py
django-bcmr/urls.py
django-bcmr/wsgi.py
django_bcmr.egg-info/PKG-INFO
django_bcmr.egg-info/SOURCES.txt
django_bcmr.egg-info/dependency_links.txt
django_bcmr.egg-info/requires.txt
django_bcmr.egg-info/top_level.txt